lazily/__init__.py
lazily/cell.py
lazily/py.typed
lazily/slot.py
lazily/types.py
lazily-0.10.2.dist-info/licenses/LICENSE
lazily-0.10.2.dist-info/METADATA
lazily-0.10.2.dist-info/WHEEL
lazily-0.10.2.dist-info/top_level.txt
lazily-0.10.2.dist-info/RECORD
