Metadata-Version: 2.4
Name: lazily
Version: 0.10.2
Summary: A library for lazy evaluation with context caching
Author-email: Brian Takita <brian.takita@gmail.com>
Maintainer-email: Brian Takita <brian.takita@gmail.com>
License:                                  Apache License
Project-URL: Homepage, https://github.com/btakita/lazily-py
Project-URL: Bug Reports, https://github.com/btakita/lazily-py/issues
Project-URL: Source, https://github.com/btakita/lazily-py
Keywords: lazy,evaluation,dependency,injection,context,lazily
Classifier: Development Status :: 3 - Alpha
Classifier: Intended Audience :: Developers
Classifier: License :: OSI Approved :: MIT License
Classifier: Programming Language :: Python :: 3
Classifier: Programming Language :: Python :: 3.12
Classifier: Programming Language :: Python :: 3.13
Classifier: Programming Language :: Python :: 3.14
Classifier: Topic :: Software Development :: Libraries :: Python Modules
Classifier: Topic :: Utilities
Requires-Python: >=3.12
License-File: LICENSE
Provides-Extra: dev
Requires-Dist: build==1.4.0; extra == "dev"
Requires-Dist: mypy==1.19.1; extra == "dev"
Requires-Dist: poethepoet==0.40.0; extra == "dev"
Requires-Dist: pytest-cov==7.0.0; extra == "dev"
Requires-Dist: pytest==9.0.2; extra == "dev"
Requires-Dist: ruff==0.14.14; extra == "dev"
Requires-Dist: twine==6.2.0; extra == "dev"
Dynamic: license-file
